d3m/domain/__init__.py
d3m/domain/bases.py
d3m/domain/collection.py
d3m/domain/command.py
d3m/domain/entities.py
d3m/domain/event.py
d3m/domain/exceptions.py
d3m/domain/py.typed
dddmisc_domain-0.6.1.dist-info/LICENSE
dddmisc_domain-0.6.1.dist-info/METADATA
dddmisc_domain-0.6.1.dist-info/WHEEL
dddmisc_domain-0.6.1.dist-info/RECORD
